napari_omero/__init__.py
napari_omero/__main__.py
napari_omero/napari.yaml
napari_omero/py.typed
napari_omero/utils.py
napari_omero/plugins/__init__.py
napari_omero/plugins/_napari.py
napari_omero/plugins/loaders.py
napari_omero/plugins/masks.py
napari_omero/plugins/omero.py
napari_omero/widgets/ROIs.py
napari_omero/widgets/__init__.py
napari_omero/widgets/gateway.py
napari_omero/widgets/login.py
napari_omero/widgets/main.py
napari_omero/widgets/thumb_grid.py
napari_omero/widgets/tree_model.py
omero/plugins/napari.py
napari_omero-0.5.1.dist-info/METADATA
napari_omero-0.5.1.dist-info/WHEEL
napari_omero-0.5.1.dist-info/entry_points.txt
napari_omero-0.5.1.dist-info/licenses/LICENSE
napari_omero-0.5.1.dist-info/RECORD
