Metadata-Version: 2.4
Name: napari-omero
Version: 0.5.1
Summary: napari/OMERO interoperability
Project-URL: homepage, https://github.com/tlambert03/napari-omero
Project-URL: repository, https://github.com/tlambert03/napari-omero
Author: Peter Sobolewski
Author-email: Talley Lambert <talley.lambert@gmail.com>, Will Moore <w.moore@dundee.ac.uk>, Johannes Soltwedel <johannes_richard.soltwedel@tu-dresden.de>
License: GPL-2.0-or-later
License-File: LICENSE
Keywords: OMERO.CLI,napari,napari-plugin,plugin
Classifier: Development Status :: 4 - Beta
Classifier: Environment :: X11 Applications :: Qt
Classifier: Framework :: napari
Classifier: Intended Audience :: Developers
Classifier: Intended Audience :: Education
Classifier: Intended Audience :: End Users/Desktop
Classifier: Intended Audience :: Science/Research
Classifier: License :: OSI Approved :: GNU General Public License v2 or later (GPLv2+)
Classifier: Natural Language :: English
Classifier: Operating System :: OS Independent
Classifier: Programming Language :: Python :: 3
Classifier: Programming Language :: Python :: 3.9
Classifier: Programming Language :: Python :: 3.10
Classifier: Programming Language :: Python :: 3.11
Classifier: Programming Language :: Python :: 3.12
Classifier: Topic :: Scientific/Engineering
Classifier: Topic :: Scientific/Engineering :: Bio-Informatics
Classifier: Topic :: Scientific/Engineering :: Information Analysis
Classifier: Topic :: Scientific/Engineering :: Visualization
Classifier: Topic :: Software Development :: Libraries :: Python Modules
Classifier: Topic :: Utilities
Classifier: Typing :: Typed
Requires-Python: >=3.9
Requires-Dist: dask[array]>=2021.10.0
Requires-Dist: napari>=0.5.0
Requires-Dist: omero-marshal
Requires-Dist: omero-py
Requires-Dist: omero-rois
Requires-Dist: qtpy>=1.10.0
Requires-Dist: superqt>=0.6.7
Provides-Extra: all
Requires-Dist: napari[all]; extra == 'all'
Provides-Extra: dev
Requires-Dist: ipython; extra == 'dev'
Requires-Dist: mypy; extra == 'dev'
Requires-Dist: napari[all]; extra == 'dev'
Requires-Dist: pdbpp; extra == 'dev'
Requires-Dist: pre-commit; extra == 'dev'
Requires-Dist: pytest; extra == 'dev'
Requires-Dist: pytest-cov; extra == 'dev'
Requires-Dist: pytest-qt; extra == 'dev'
Requires-Dist: pytest-regressions; extra == 'dev'
Requires-Dist: pywin32; (sys_platform == 'win32') and extra == 'dev'
Requires-Dist: rich; extra == 'dev'
Requires-Dist: ruff; extra == 'dev'
Provides-Extra: test
Requires-Dist: pytest; extra == 'test'
Requires-Dist: pytest-cov; extra == 'test'
Requires-Dist: pytest-qt; extra == 'test'
Requires-Dist: pytest-regressions; extra == 'test'
Requires-Dist: pywin32; (sys_platform == 'win32') and extra == 'test'
